Metadata-Version: 2.1
Name: gcalendar
Version: 0.2
Summary: Read Google Calendar events from your terminal.
Home-page: https://github.com/slgobinath/gcalendar
Author: Gobinath Loganathan
Author-email: slgobinath@gmail.com
License: UNKNOWN
Download-URL: https://github.com/slgobinath/gcalendar/archive/v0.2.tar.gz
Keywords: linux utility google-calendar
Platform: UNKNOWN
Classifier: Operating System :: POSIX :: Linux
Classifier: License :: OSI Approved :: GNU General Public License v3 (GPLv3)
Classifier: Development Status :: 5 - Production/Stable
Classifier: Environment :: X11 Applications :: GTK
Classifier: Intended Audience :: End Users/Desktop
Classifier: Topic :: Utilities
Classifier: Programming Language :: Python :: 3
Classifier: Programming Language :: Python :: 3.4
Classifier: Programming Language :: Python :: 3.5
Classifier: Programming Language :: Python :: 3.6
Classifier: Programming Language :: Python :: 3.7
